{
  "source_file": "event_mes_data_0953.hav",
  "container_index": 953,
  "entry_count": 18,
  "pointer_size": 2,
  "null_chunk": false,
  "entries": [
    {
      "index": 0,
      "name": "0",
      "message": "[RAW:401F-1320-A91F-481F-3521-1420]あっ、こら待てっ！！[RAW:0E27]",
      "original": "[RAW:401F-1320-A91F-481F-3521-1420]あっ、こら待てっ！！[RAW:0E27]",
      "translation": "[RAW:401F-1320-A91F-481F-3521-1420]앗、야　기다려！！[RAW:0E27]",
      "controls": [
        "[RAW:401F-1320-A91F-481F-3521-1420]",
        "[RAW:0E27]"
      ]
    },
    {
      "index": 1,
      "name": "1",
      "message": "[RAW:411F-AE1F-4B1F-3621-2A23]さんっ！[RAW:2823-2A23]さんっ！？[RAW:2B23-401F-A91F-4A1F-3521]ナナさん！[RAW:2823-2A23]！！[RAW:2B23-411F-AE1F-4B1F-3621]キリクくん！[RAW:2823-2A23]さんが、川に…！[RAW:0E27]",
      "original": "[RAW:411F-AE1F-4B1F-3621-2A23]さんっ！[RAW:2823-2A23]さんっ！？[RAW:2B23-401F-A91F-4A1F-3521]ナナさん！[RAW:2823-2A23]！！[RAW:2B23-411F-AE1F-4B1F-3621]キリクくん！[RAW:2823-2A23]さんが、川に…！[RAW:0E27]",
      "translation": "[RAW:411F-AE1F-4B1F-3621-2B23]님！[RAW:2B23]님！？[RAW:2A23-401F-A91F-4A1F-3521-2823]나나　씨！[RAW:2A23]！！[RAW:2A23-411F-AE1F-4B1F-3621-2823]키리쿠　군！[RAW:2A23]님이、[RAW:2823]강에…！[RAW:0E27]",
      "controls": [
        "[RAW:411F-AE1F-4B1F-3621-2A23]",
        "[RAW:2823-2A23]",
        "[RAW:2B23-401F-A91F-4A1F-3521]",
        "[RAW:2823-2A23]",
        "[RAW:2B23-411F-AE1F-4B1F-3621]",
        "[RAW:2823-2A23]",
        "[RAW:0E27]"
      ]
    },
    {
      "index": 2,
      "name": "2",
      "message": "[RAW:411F-AE1F-4B1F-3621-2A23]さん…！[RAW:2823]大丈夫！？[RAW:0E27]",
      "original": "[RAW:411F-AE1F-4B1F-3621-2A23]さん…！[RAW:2823]大丈夫！？[RAW:0E27]",
      "translation": "[RAW:411F-AE1F-4B1F-3621-2A23]님…！[RAW:2823]괜찮아요！？[RAW:0E27]",
      "controls": [
        "[RAW:411F-AE1F-4B1F-3621-2A23]",
        "[RAW:2823]",
        "[RAW:0E27]"
      ]
    },
    {
      "index": 3,
      "name": "3",
      "message": "[RAW:411F-A91F-4B1F-3621]ごめんな、[RAW:2A23]。[RAW:2B23]コイツ、ふろをいやがって、[RAW:2823]パニックになっちまってさ…。[RAW:2823]コイツに悪気はなかったんだ。[RAW:0E27]",
      "original": "[RAW:411F-A91F-4B1F-3621]ごめんな、[RAW:2A23]。[RAW:2B23]コイツ、ふろをいやがって、[RAW:2823]パニックになっちまってさ…。[RAW:2823]コイツに悪気はなかったんだ。[RAW:0E27]",
      "translation": "[RAW:411F-A91F-4B1F-3621]미안해、[RAW:2A23]。[RAW:2B23]얘가　목욕을　싫어해서、[RAW:2823]패닉이　와　버렸거든…。[RAW:2823]나쁜　뜻은　없었어。[RAW:0E27]",
      "controls": [
        "[RAW:411F-A91F-4B1F-3621]",
        "[RAW:2A23]",
        "[RAW:2B23]",
        "[RAW:2823]",
        "[RAW:2823]",
        "[RAW:0E27]"
      ]
    },
    {
      "index": 4,
      "name": "4",
      "message": "[RAW:411F-A91F-491F-3621]ゆるしてもらえて、[RAW:2823]良かったな。[RAW:2B23-411F-A91F-481F-3621]それじゃ今度こそ、[RAW:2823]わがまま言わずに[RAW:2823]ふろに入るんだぞ。[RAW:0E27]",
      "original": "[RAW:411F-A91F-491F-3621]ゆるしてもらえて、[RAW:2823]良かったな。[RAW:2B23-411F-A91F-481F-3621]それじゃ今度こそ、[RAW:2823]わがまま言わずに[RAW:2823]ふろに入るんだぞ。[RAW:0E27]",
      "translation": "[RAW:411F-A91F-491F-3621]용서받아서、[RAW:2823]다행이네。[RAW:2B23-411F-A91F-481F-3621]그럼　이번에야말로、[RAW:2823]투정　부리지　말고[RAW:2823]목욕해야　한다？[RAW:0E27]",
      "controls": [
        "[RAW:411F-A91F-491F-3621]",
        "[RAW:2823]",
        "[RAW:2B23-411F-A91F-481F-3621]",
        "[RAW:2823]",
        "[RAW:2823]",
        "[RAW:0E27]"
      ]
    },
    {
      "index": 5,
      "name": "5",
      "message": "[RAW:411F-A91F-481F-3621]よーし！　良い子だ。[RAW:2B23-411F-A91F-4C1F-3621-2A23]、ナナさん、[RAW:2823]本当に悪かったな。[RAW:2B23-411F-A91F-481F-3621]それじゃ、オレは[RAW:2823]コイツをふろに入れに帰るよ。[RAW:0E27]",
      "original": "[RAW:411F-A91F-481F-3621]よーし！　良い子だ。[RAW:2B23-411F-A91F-4C1F-3621-2A23]、ナナさん、[RAW:2823]本当に悪かったな。[RAW:2B23-411F-A91F-481F-3621]それじゃ、オレは[RAW:2823]コイツをふろに入れに帰るよ。[RAW:0E27]",
      "translation": "[RAW:411F-A91F-481F-3621]좋았어！　착하지。[RAW:2B23-411F-A91F-4C1F-3621-2A23]、나나　씨、[RAW:2823]정말　미안했어。[RAW:2B23-411F-A91F-481F-3621]그럼　난[RAW:2823]얘　목욕시키러　갈게。[RAW:0E27]",
      "controls": [
        "[RAW:411F-A91F-481F-3621]",
        "[RAW:2B23-411F-A91F-4C1F-3621-2A23]",
        "[RAW:2823]",
        "[RAW:2B23-411F-A91F-481F-3621]",
        "[RAW:2823]",
        "[RAW:0E27]"
      ]
    },
    {
      "index": 6,
      "name": "6",
      "message": "[RAW:411F-AE1F-4B1F-3621]ごめんなさい、[RAW:2823-2A23]さん…。[RAW:2B23]わたしをかばって、[RAW:2823]こんな事になってしまって。[RAW:0E27]",
      "original": "[RAW:411F-AE1F-4B1F-3621]ごめんなさい、[RAW:2823-2A23]さん…。[RAW:2B23]わたしをかばって、[RAW:2823]こんな事になってしまって。[RAW:0E27]",
      "translation": "[RAW:411F-AE1F-4B1F-3621]죄송해요、[RAW:2A23]님…。[RAW:2B23]저를　감싸다가、[RAW:2823]이렇게　돼[RAW:2823]버려서。[RAW:0E27]",
      "controls": [
        "[RAW:411F-AE1F-4B1F-3621]",
        "[RAW:2823-2A23]",
        "[RAW:2B23]",
        "[RAW:2823]",
        "[RAW:0E27]"
      ]
    },
    {
      "index": 7,
      "name": "7",
      "message": "[RAW:3223-0008]全然平気だよ！[RAW:2823-0008]女の子を守るのは当たり前！[RAW:0E27]",
      "original": "[RAW:3223-0008]全然平気だよ！[RAW:2823-0008]女の子を守るのは当たり前！[RAW:0E27]",
      "translation": "[RAW:3223-0008]전혀　안　아파！[RAW:2823-0008]여자애는　지켜야지！[RAW:0E27]",
      "controls": [
        "[RAW:3223-0008]",
        "[RAW:2823-0008]",
        "[RAW:0E27]"
      ]
    },
    {
      "index": 8,
      "name": "8",
      "message": "[RAW:411F-AE1F-4D1F-3621]…ありがとう。[RAW:2823-2A23]さん。[RAW:2B23-411F-AE1F-481F-3621]………でも。[RAW:0E27]",
      "original": "[RAW:411F-AE1F-4D1F-3621]…ありがとう。[RAW:2823-2A23]さん。[RAW:2B23-411F-AE1F-481F-3621]………でも。[RAW:0E27]",
      "translation": "[RAW:411F-AE1F-4D1F-3621]…고마워요。[RAW:2B23]님。[RAW:2A23-411F-AE1F-481F-3621-2823]………하지만。[RAW:0E27]",
      "controls": [
        "[RAW:411F-AE1F-4D1F-3621]",
        "[RAW:2823-2A23]",
        "[RAW:2B23-411F-AE1F-481F-3621]",
        "[RAW:0E27]"
      ]
    },
    {
      "index": 9,
      "name": "9",
      "message": "[RAW:411F-AE1F-4B1F-3621]ここ…。[RAW:2823]ケガしてしまったわね。[RAW:2B23-411F-AE1F-481F-3621]助けてくれるのは、[RAW:2823]とてもうれしいけれど…[RAW:2823]ムリはしないで。[RAW:2B23-411F-AE1F-4B1F-3621]あなたが川に落ちた時は[RAW:2823]わたし、本当に心配したのよ。[RAW:0E27]",
      "original": "[RAW:411F-AE1F-4B1F-3621]ここ…。[RAW:2823]ケガしてしまったわね。[RAW:2B23-411F-AE1F-481F-3621]助けてくれるのは、[RAW:2823]とてもうれしいけれど…[RAW:2823]ムリはしないで。[RAW:2B23-411F-AE1F-4B1F-3621]あなたが川に落ちた時は[RAW:2823]わたし、本当に心配したのよ。[RAW:0E27]",
      "translation": "[RAW:411F-AE1F-4B1F-3621]여기…。[RAW:2823]다쳐　버렸네요。[RAW:2B23-411F-AE1F-481F-3621]도와주는　건、[RAW:2823]정말　기쁘지만…[RAW:2823]무리는　하지　마세요。[RAW:2B23-411F-AE1F-4B1F-3621]당신이　강에　빠졌을　땐[RAW:2823]저、정말　걱정했어요。[RAW:0E27]",
      "controls": [
        "[RAW:411F-AE1F-4B1F-3621]",
        "[RAW:2823]",
        "[RAW:2B23-411F-AE1F-481F-3621]",
        "[RAW:2823]",
        "[RAW:2823]",
        "[RAW:2B23-411F-AE1F-4B1F-3621]",
        "[RAW:2823]",
        "[RAW:0E27]"
      ]
    },
    {
      "index": 10,
      "name": "10",
      "message": "[RAW:411F-AE1F-481F-3621]応急手当はしておいたけれど[RAW:2823]念のため、後でアヤメさんに[RAW:2823]みてもらって。[RAW:0E27]",
      "original": "[RAW:411F-AE1F-481F-3621]応急手当はしておいたけれど[RAW:2823]念のため、後でアヤメさんに[RAW:2823]みてもらって。[RAW:0E27]",
      "translation": "[RAW:411F-AE1F-481F-3621]응급처치는　했지만[RAW:2823]혹시　모르니　나중에[RAW:2823]아야메　씨께　보여　줘。[RAW:0E27]",
      "controls": [
        "[RAW:411F-AE1F-481F-3621]",
        "[RAW:2823]",
        "[RAW:2823]",
        "[RAW:0E27]"
      ]
    },
    {
      "index": 11,
      "name": "11",
      "message": "[RAW:411F-AE1F-491F-3621]フフッ、良いお返事ね。[RAW:0E27]",
      "original": "[RAW:411F-AE1F-491F-3621]フフッ、良いお返事ね。[RAW:0E27]",
      "translation": "[RAW:411F-AE1F-491F-3621]후훗、좋은　대답이네요。[RAW:0E27]",
      "controls": [
        "[RAW:411F-AE1F-491F-3621]",
        "[RAW:0E27]"
      ]
    },
    {
      "index": 12,
      "name": "12",
      "message": "[RAW:411F-AE1F-481F-3621]それにしても…。[RAW:2B23-411F-AE1F-491F-3621]今日は、[RAW:2A23]さんが[RAW:2823]本当に優しい人だって事が[RAW:2823]よくわかったわ。[RAW:2B23-411F-AE1F-4D1F-3621]……優しいだけじゃなくて、[RAW:2823]じつは、すごく頼りになる[RAW:2823]男の人なんだなって事も。[RAW:0E27]",
      "original": "[RAW:411F-AE1F-481F-3621]それにしても…。[RAW:2B23-411F-AE1F-491F-3621]今日は、[RAW:2A23]さんが[RAW:2823]本当に優しい人だって事が[RAW:2823]よくわかったわ。[RAW:2B23-411F-AE1F-4D1F-3621]……優しいだけじゃなくて、[RAW:2823]じつは、すごく頼りになる[RAW:2823]男の人なんだなって事も。[RAW:0E27]",
      "translation": "[RAW:411F-AE1F-481F-3621]그래도…。[RAW:2B23-411F-AE1F-491F-3621]오늘은、[RAW:2A23]님이[RAW:2823]정말　상냥한　분이라는　걸[RAW:2823]잘　알게　됐어요。[RAW:2B23-411F-AE1F-4D1F-3621]……상냥할　뿐　아니라、[RAW:2823]사실은　정말　든든한[RAW:2823]남자란　것도요。[RAW:0E27]",
      "controls": [
        "[RAW:411F-AE1F-481F-3621]",
        "[RAW:2B23-411F-AE1F-491F-3621]",
        "[RAW:2A23]",
        "[RAW:2823]",
        "[RAW:2823]",
        "[RAW:2B23-411F-AE1F-4D1F-3621]",
        "[RAW:2823]",
        "[RAW:2823]",
        "[RAW:0E27]"
      ]
    },
    {
      "index": 13,
      "name": "13",
      "message": "[RAW:411F-AE1F-491F-3621]いいえ、何でもないわ。[RAW:2823]気にしないで。[RAW:0E27]",
      "original": "[RAW:411F-AE1F-491F-3621]いいえ、何でもないわ。[RAW:2823]気にしないで。[RAW:0E27]",
      "translation": "[RAW:411F-AE1F-491F-3621]아니에요、아무것도　아녜요。[RAW:2823]신경　쓰지　마세요。[RAW:0E27]",
      "controls": [
        "[RAW:411F-AE1F-491F-3621]",
        "[RAW:2823]",
        "[RAW:0E27]"
      ]
    },
    {
      "index": 14,
      "name": "14",
      "message": "[RAW:411F-AE1F-481F-3621]さ、あなたのケガも[RAW:2823]みてもらわなくてはいけないし[RAW:2823]今日はもう帰りましょう？[RAW:0E27]",
      "original": "[RAW:411F-AE1F-481F-3621]さ、あなたのケガも[RAW:2823]みてもらわなくてはいけないし[RAW:2823]今日はもう帰りましょう？[RAW:0E27]",
      "translation": "[RAW:411F-AE1F-481F-3621]자、당신　상처도[RAW:2823]봐야　하니까、[RAW:2823]오늘은　돌아가죠？[RAW:0E27]",
      "controls": [
        "[RAW:411F-AE1F-481F-3621]",
        "[RAW:2823]",
        "[RAW:2823]",
        "[RAW:0E27]"
      ]
    },
    {
      "index": 15,
      "name": "15",
      "message": "[RAW:411F-AE1F-4C1F-3621]そう…、そうね。[RAW:2823]あなたはいつも、だれにでも[RAW:2823]変わりなく優しいものね。[RAW:2B23-411F-AE1F-491F-3621]やだ、わたしったら。[RAW:2823]１人で勝手にかんちがいをして[RAW:2823]しまっていたみたい。[RAW:0E27]",
      "original": "[RAW:411F-AE1F-4C1F-3621]そう…、そうね。[RAW:2823]あなたはいつも、だれにでも[RAW:2823]変わりなく優しいものね。[RAW:2B23-411F-AE1F-491F-3621]やだ、わたしったら。[RAW:2823]１人で勝手にかんちがいをして[RAW:2823]しまっていたみたい。[RAW:0E27]",
      "translation": "[RAW:411F-AE1F-4C1F-3621]그래…、그러네요。[RAW:2823]당신은　언제나、누구에게나[RAW:2823]한결같이　상냥하네요。[RAW:2B23-411F-AE1F-491F-3621]어머、저도　참。[RAW:2823]혼자　멋대로　착각하고[RAW:2823]있었나　봐요。[RAW:0E27]",
      "controls": [
        "[RAW:411F-AE1F-4C1F-3621]",
        "[RAW:2823]",
        "[RAW:2823]",
        "[RAW:2B23-411F-AE1F-491F-3621]",
        "[RAW:2823]",
        "[RAW:2823]",
        "[RAW:0E27]"
      ]
    },
    {
      "index": 16,
      "name": "16",
      "message": "[RAW:411F-AE1F-491F-3621]いいえ、何でもないの。[RAW:2B23-411F-AE1F-481F-3621]とにかく、さっきは[RAW:2823]ありがとう[RAW:2A23]さん。[RAW:2823]とても助かったわ。[RAW:2B23]わたしを、[RAW:2823]女の子あつかいしてくれたのも[RAW:2823]すごくうれしかった。[RAW:2B23-411F-AE1F-4B1F-3621]でも、わたし……。[RAW:0E27]",
      "original": "[RAW:411F-AE1F-491F-3621]いいえ、何でもないの。[RAW:2B23-411F-AE1F-481F-3621]とにかく、さっきは[RAW:2823]ありがとう[RAW:2A23]さん。[RAW:2823]とても助かったわ。[RAW:2B23]わたしを、[RAW:2823]女の子あつかいしてくれたのも[RAW:2823]すごくうれしかった。[RAW:2B23-411F-AE1F-4B1F-3621]でも、わたし……。[RAW:0E27]",
      "translation": "[RAW:411F-AE1F-491F-3621]아니에요、별거　아녜요。[RAW:2B23-411F-AE1F-481F-3621]아무튼、아까는[RAW:2823]고마웠어요[RAW:2A23]님。[RAW:2823]정말　큰　도움이　됐어요。[RAW:2B23]저를、[RAW:2823]여자애로　대해　준　것도[RAW:2823]정말　기뻤어요。[RAW:2B23-411F-AE1F-4B1F-3621]하지만、저는……。[RAW:0E27]",
      "controls": [
        "[RAW:411F-AE1F-491F-3621]",
        "[RAW:2B23-411F-AE1F-481F-3621]",
        "[RAW:2823]",
        "[RAW:2A23]",
        "[RAW:2823]",
        "[RAW:2B23]",
        "[RAW:2823]",
        "[RAW:2823]",
        "[RAW:2B23-411F-AE1F-4B1F-3621]",
        "[RAW:0E27]"
      ]
    },
    {
      "index": 17,
      "name": "17",
      "message": "[RAW:411F-AE1F-491F-3621]ご、ごめんなさい。何だか[RAW:2823]今日は調子が悪いみたい。[RAW:2823]帰るわね！[RAW:0E27-0F27]～",
      "original": "[RAW:411F-AE1F-491F-3621]ご、ごめんなさい。何だか[RAW:2823]今日は調子が悪いみたい。[RAW:2823]帰るわね！[RAW:0E27-0F27]～",
      "translation": "[RAW:411F-AE1F-491F-3621]죄、죄송해요。왠지[RAW:2823]오늘은　상태가　안　좋네요。[RAW:2823]먼저　갈게요！[RAW:0E27-0F27]～",
      "controls": [
        "[RAW:411F-AE1F-491F-3621]",
        "[RAW:2823]",
        "[RAW:2823]",
        "[RAW:0E27-0F27]"
      ]
    }
  ]
}