{
  "source_file": "event_mes_data_1851.hav",
  "container_index": 1851,
  "entry_count": 21,
  "pointer_size": 2,
  "null_chunk": false,
  "entries": [
    {
      "index": 0,
      "name": "0",
      "message": "[RAW:411F-C61F-481F-3621-6D20]★ＥＲＲＯＲ！★[RAW:6C20-0E27]",
      "original": "[RAW:411F-C61F-481F-3621-6D20]★ＥＲＲＯＲ！★[RAW:6C20-0E27]",
      "translation": "[RAW:411F-C61F-481F-3621-6D20]★ＥＲＲＯＲ！★[RAW:6C20-0E27]",
      "controls": [
        "[RAW:411F-C61F-481F-3621-6D20]",
        "[RAW:6C20-0E27]"
      ]
    },
    {
      "index": 1,
      "name": "1",
      "message": "[RAW:411F-AE1F-481F-3621]けいじ板を[RAW:2823]見てくれたのね。[RAW:2B23-411F-AE1F-4B1F]ただ、もうこんな時間だし、[RAW:2823]また今度に[RAW:2823]お願いすることにするわ。[RAW:2B23]自分の牧場でいそがしいのに[RAW:2823]…ごめんなさいね。[RAW:0E27]",
      "original": "[RAW:411F-AE1F-481F-3621]けいじ板を[RAW:2823]見てくれたのね。[RAW:2B23-411F-AE1F-4B1F]ただ、もうこんな時間だし、[RAW:2823]また今度に[RAW:2823]お願いすることにするわ。[RAW:2B23]自分の牧場でいそがしいのに[RAW:2823]…ごめんなさいね。[RAW:0E27]",
      "translation": "[RAW:411F-AE1F-481F-3621]게시판을[RAW:2823]봐 줬구나。[RAW:2B23-411F-AE1F-4B1F]다만、벌써 이런 시간이니、[RAW:2823]다음에[RAW:2823]부탁하기로 할게。[RAW:2B23]네 목장 일로 바쁠 텐데[RAW:2823]…미안해。[RAW:0E27]",
      "controls": [
        "[RAW:411F-AE1F-481F-3621]",
        "[RAW:2823]",
        "[RAW:2B23-411F-AE1F-4B1F]",
        "[RAW:2823]",
        "[RAW:2823]",
        "[RAW:2B23]",
        "[RAW:2823]",
        "[RAW:0E27]"
      ]
    },
    {
      "index": 2,
      "name": "2",
      "message": "[RAW:411F-AE1F-481F-3621]けいじ板を[RAW:2823]見てくれたのね。[RAW:2B23-411F-AE1F-4B1F]ただ、雨がふったから[RAW:2823]水まきしなくても[RAW:2823]よくなっちゃったわね…。[RAW:2B23-411F-AE1F-491F]せめて、お礼だけでも[RAW:2823]受け取ってちょうだい？[RAW:0E27]",
      "original": "[RAW:411F-AE1F-481F-3621]けいじ板を[RAW:2823]見てくれたのね。[RAW:2B23-411F-AE1F-4B1F]ただ、雨がふったから[RAW:2823]水まきしなくても[RAW:2823]よくなっちゃったわね…。[RAW:2B23-411F-AE1F-491F]せめて、お礼だけでも[RAW:2823]受け取ってちょうだい？[RAW:0E27]",
      "translation": "[RAW:411F-AE1F-481F-3621]게시판을[RAW:2823]봐 줬구나。[RAW:2B23-411F-AE1F-4B1F]다만、비가 와서[RAW:2823]물 주지 않아도[RAW:2823]괜찮아졌네…。[RAW:2B23-411F-AE1F-491F]답례만이라도[RAW:2823]받아 주겠니？[RAW:0E27]",
      "controls": [
        "[RAW:411F-AE1F-481F-3621]",
        "[RAW:2823]",
        "[RAW:2B23-411F-AE1F-4B1F]",
        "[RAW:2823]",
        "[RAW:2823]",
        "[RAW:2B23-411F-AE1F-491F]",
        "[RAW:2823]",
        "[RAW:0E27]"
      ]
    },
    {
      "index": 3,
      "name": "3",
      "message": "[RAW:411F-AE1F-491F-3621]けいじ板を[RAW:2823]見てくれたのね。ありがとう。[RAW:2B23]じゃあ、さっそく[RAW:2823]はじめましょうか。[RAW:0E27]",
      "original": "[RAW:411F-AE1F-491F-3621]けいじ板を[RAW:2823]見てくれたのね。ありがとう。[RAW:2B23]じゃあ、さっそく[RAW:2823]はじめましょうか。[RAW:0E27]",
      "translation": "[RAW:411F-AE1F-491F-3621]게시판을[RAW:2823]봐 줬구나。고마워。[RAW:2B23]그럼、바로[RAW:2823]시작해 볼까。[RAW:0E27]",
      "controls": [
        "[RAW:411F-AE1F-491F-3621]",
        "[RAW:2823]",
        "[RAW:2B23]",
        "[RAW:2823]",
        "[RAW:0E27]"
      ]
    },
    {
      "index": 4,
      "name": "4",
      "message": "[RAW:411F-AE1F-491F-3621]ここが畑よ。[RAW:2823]フフッ。[RAW:2823]なかなか立派でしょう？[RAW:2B23]この畑に[RAW:2823-6D20]水まき[RAW:6C20]をお願いしたいの。[RAW:2B23-411F-AE1F-481F]こんなに寒い季節だもの。[RAW:2823]おじいちゃんには１日くらい[RAW:2823]休んでほしかったの。[RAW:2B23-411F-AE1F-491F]あなたも、自分の牧場で[RAW:2823]いそがしいのに、おつかいを[RAW:2823]うけてくれてうれしいわ。[RAW:2B23]それじゃあ、[RAW:2823]終わったら教えてね。[RAW:0E27]",
      "original": "[RAW:411F-AE1F-491F-3621]ここが畑よ。[RAW:2823]フフッ。[RAW:2823]なかなか立派でしょう？[RAW:2B23]この畑に[RAW:2823-6D20]水まき[RAW:6C20]をお願いしたいの。[RAW:2B23-411F-AE1F-481F]こんなに寒い季節だもの。[RAW:2823]おじいちゃんには１日くらい[RAW:2823]休んでほしかったの。[RAW:2B23-411F-AE1F-491F]あなたも、自分の牧場で[RAW:2823]いそがしいのに、おつかいを[RAW:2823]うけてくれてうれしいわ。[RAW:2B23]それじゃあ、[RAW:2823]終わったら教えてね。[RAW:0E27]",
      "translation": "[RAW:411F-AE1F-491F-3621]여기가 밭이야。[RAW:2823]후훗。[RAW:2823]꽤 훌륭하지？[RAW:2B23]이 밭에[RAW:2823-6D20]물 주기[RAW:6C20]를 부탁하고 싶어。[RAW:2B23-411F-AE1F-481F]이렇게 추운 계절인걸。[RAW:2823]할아버지께 하루쯤[RAW:2823]쉬게 해 드리고 싶었어。[RAW:2B23-411F-AE1F-491F]너도、네 목장에서[RAW:2823]바쁠 텐데、심부름을[RAW:2823]맡아 줘서 기뻐。[RAW:2B23]그럼、[RAW:2823]끝나면 알려 줘。[RAW:0E27]",
      "controls": [
        "[RAW:411F-AE1F-491F-3621]",
        "[RAW:2823]",
        "[RAW:2823]",
        "[RAW:2B23]",
        "[RAW:2823-6D20]",
        "[RAW:6C20]",
        "[RAW:2B23-411F-AE1F-481F]",
        "[RAW:2823]",
        "[RAW:2823]",
        "[RAW:2B23-411F-AE1F-491F]",
        "[RAW:2823]",
        "[RAW:2823]",
        "[RAW:2B23]",
        "[RAW:2823]",
        "[RAW:0E27]"
      ]
    },
    {
      "index": 5,
      "name": "5",
      "message": "[RAW:411F-AE1F-491F-3621]ここが畑よ。[RAW:2823]フフッ。[RAW:2823]なかなか立派でしょう？[RAW:2B23-411F-AE1F-481F]この畑の作物を[RAW:2823-6D20]収穫[RAW:6C20]してほしいの。[RAW:2B23]あ、収穫した作物は[RAW:6D20]自動的に[RAW:2823]おじいちゃんのそうこに[RAW:2823]送られる[RAW:6C20]から、安心して。[RAW:2823-2B23-411F-AE1F-481F]こんなに寒い季節だもの。[RAW:2823]おじいちゃんには１日くらい[RAW:2823]休んでほしかったの。[RAW:2B23-411F-AE1F-491F]あなたも、自分の牧場で[RAW:2823]いそがしいのに、おつかいを[RAW:2823]うけてくれてうれしいわ。[RAW:2B23]それじゃあ、[RAW:2823]終わったら教えてね。[RAW:0E27]",
      "original": "[RAW:411F-AE1F-491F-3621]ここが畑よ。[RAW:2823]フフッ。[RAW:2823]なかなか立派でしょう？[RAW:2B23-411F-AE1F-481F]この畑の作物を[RAW:2823-6D20]収穫[RAW:6C20]してほしいの。[RAW:2B23]あ、収穫した作物は[RAW:6D20]自動的に[RAW:2823]おじいちゃんのそうこに[RAW:2823]送られる[RAW:6C20]から、安心して。[RAW:2823-2B23-411F-AE1F-481F]こんなに寒い季節だもの。[RAW:2823]おじいちゃんには１日くらい[RAW:2823]休んでほしかったの。[RAW:2B23-411F-AE1F-491F]あなたも、自分の牧場で[RAW:2823]いそがしいのに、おつかいを[RAW:2823]うけてくれてうれしいわ。[RAW:2B23]それじゃあ、[RAW:2823]終わったら教えてね。[RAW:0E27]",
      "translation": "[RAW:411F-AE1F-491F-3621]여기가 밭이야。[RAW:2823]후훗。[RAW:2823]꽤 훌륭하지？[RAW:2B23-411F-AE1F-481F]이 밭의 작물을[RAW:2823-6D20]수확[RAW:6C20]해 줬으면 해。[RAW:2B23]아、수확한 작물은 [RAW:6D20]자동으로[RAW:2823]할아버지의 창고에[RAW:2823]보내질[RAW:6C20] 테니、안심해。[RAW:2B23-2823-411F-AE1F-481F]이렇게 추운 계절인걸。[RAW:2823]할아버지께 하루쯤[RAW:2823]쉬게 해 드리고 싶었어。[RAW:2B23-411F-AE1F-491F]너도、네 목장에서[RAW:2823]바쁠 텐데、심부름을[RAW:2823]맡아 줘서 기뻐。[RAW:2B23]그럼、[RAW:2823]끝나면 알려 줘。[RAW:0E27]",
      "controls": [
        "[RAW:411F-AE1F-491F-3621]",
        "[RAW:2823]",
        "[RAW:2823]",
        "[RAW:2B23-411F-AE1F-481F]",
        "[RAW:2823-6D20]",
        "[RAW:6C20]",
        "[RAW:2B23]",
        "[RAW:6D20]",
        "[RAW:2823]",
        "[RAW:2823]",
        "[RAW:6C20]",
        "[RAW:2823-2B23-411F-AE1F-481F]",
        "[RAW:2823]",
        "[RAW:2823]",
        "[RAW:2B23-411F-AE1F-491F]",
        "[RAW:2823]",
        "[RAW:2823]",
        "[RAW:2B23]",
        "[RAW:2823]",
        "[RAW:0E27]"
      ]
    },
    {
      "index": 6,
      "name": "6",
      "message": "[RAW:411F-C61F-481F-3621-6D20]★ＥＲＲＯＲ！★[RAW:6C20-0E27]",
      "original": "[RAW:411F-C61F-481F-3621-6D20]★ＥＲＲＯＲ！★[RAW:6C20-0E27]",
      "translation": "[RAW:411F-C61F-481F-3621-6D20]★ＥＲＲＯＲ！★[RAW:6C20-0E27]",
      "controls": [
        "[RAW:411F-C61F-481F-3621-6D20]",
        "[RAW:6C20-0E27]"
      ]
    },
    {
      "index": 7,
      "name": "7",
      "message": "[RAW:411F-C61F-481F-3621-6D20]★ＥＲＲＯＲ！★[RAW:6C20-0E27]",
      "original": "[RAW:411F-C61F-481F-3621-6D20]★ＥＲＲＯＲ！★[RAW:6C20-0E27]",
      "translation": "[RAW:411F-C61F-481F-3621-6D20]★ＥＲＲＯＲ！★[RAW:6C20-0E27]",
      "controls": [
        "[RAW:411F-C61F-481F-3621-6D20]",
        "[RAW:6C20-0E27]"
      ]
    },
    {
      "index": 8,
      "name": "8",
      "message": "[RAW:411F-C61F-481F-3621-6D20]★ＥＲＲＯＲ！★[RAW:6C20-0E27]",
      "original": "[RAW:411F-C61F-481F-3621-6D20]★ＥＲＲＯＲ！★[RAW:6C20-0E27]",
      "translation": "[RAW:411F-C61F-481F-3621-6D20]★ＥＲＲＯＲ！★[RAW:6C20-0E27]",
      "controls": [
        "[RAW:411F-C61F-481F-3621-6D20]",
        "[RAW:6C20-0E27]"
      ]
    },
    {
      "index": 9,
      "name": "9",
      "message": "[RAW:411F-C61F-481F-3621-6D20]★ＥＲＲＯＲ！★[RAW:6C20-0E27]",
      "original": "[RAW:411F-C61F-481F-3621-6D20]★ＥＲＲＯＲ！★[RAW:6C20-0E27]",
      "translation": "[RAW:411F-C61F-481F-3621-6D20]★ＥＲＲＯＲ！★[RAW:6C20-0E27]",
      "controls": [
        "[RAW:411F-C61F-481F-3621-6D20]",
        "[RAW:6C20-0E27]"
      ]
    },
    {
      "index": 10,
      "name": "10",
      "message": "[RAW:411F-AE1F-491F-3621]お仕事が[RAW:2823]終わったのね。[RAW:2823]ご苦労さま！[RAW:2B23]じゃあ、お礼をあげなきゃね。[RAW:2823]ついてきてちょうだい。[RAW:0E27]",
      "original": "[RAW:411F-AE1F-491F-3621]お仕事が[RAW:2823]終わったのね。[RAW:2823]ご苦労さま！[RAW:2B23]じゃあ、お礼をあげなきゃね。[RAW:2823]ついてきてちょうだい。[RAW:0E27]",
      "translation": "[RAW:411F-AE1F-491F-3621]일이[RAW:2823]끝났구나。[RAW:2823]수고했어！[RAW:2B23]그럼、답례를 줘야지。[RAW:2823]따라와 줘。[RAW:0E27]",
      "controls": [
        "[RAW:411F-AE1F-491F-3621]",
        "[RAW:2823]",
        "[RAW:2823]",
        "[RAW:2B23]",
        "[RAW:2823]",
        "[RAW:0E27]"
      ]
    },
    {
      "index": 11,
      "name": "11",
      "message": "[RAW:411F-AE1F-481F-3621]あらあら。[RAW:2823]お仕事が終わったのね。[RAW:2823]ご苦労さまでした。[RAW:2B23-411F-AE1F-4B1F]ただ、もう少し早めに[RAW:2823]教えてほしかったわ…。[RAW:2B23]ちゃんと終わったのかしら…と[RAW:2823]心配していたのよ。[RAW:2B23-411F-AE1F-481F]じゃあ、お礼をあげなきゃね。[RAW:2823]ついてきてちょうだい。[RAW:0E27]",
      "original": "[RAW:411F-AE1F-481F-3621]あらあら。[RAW:2823]お仕事が終わったのね。[RAW:2823]ご苦労さまでした。[RAW:2B23-411F-AE1F-4B1F]ただ、もう少し早めに[RAW:2823]教えてほしかったわ…。[RAW:2B23]ちゃんと終わったのかしら…と[RAW:2823]心配していたのよ。[RAW:2B23-411F-AE1F-481F]じゃあ、お礼をあげなきゃね。[RAW:2823]ついてきてちょうだい。[RAW:0E27]",
      "translation": "[RAW:411F-AE1F-481F-3621]어머나。[RAW:2823]일이 끝났구나。[RAW:2823]수고했어。[RAW:2B23-411F-AE1F-4B1F]다만、좀 더 일찍[RAW:2823]알려 줬으면 했어…。[RAW:2B23]제대로 끝난 걸까… 하고[RAW:2823]걱정하고 있었어。[RAW:2B23-411F-AE1F-481F]그럼、답례를 줘야지。[RAW:2823]따라와 줘。[RAW:0E27]",
      "controls": [
        "[RAW:411F-AE1F-481F-3621]",
        "[RAW:2823]",
        "[RAW:2823]",
        "[RAW:2B23-411F-AE1F-4B1F]",
        "[RAW:2823]",
        "[RAW:2B23]",
        "[RAW:2823]",
        "[RAW:2B23-411F-AE1F-481F]",
        "[RAW:2823]",
        "[RAW:0E27]"
      ]
    },
    {
      "index": 12,
      "name": "12",
      "message": "[RAW:411F-AE1F-481F-3621]あらあら。[RAW:2823]お仕事が終わったのね。[RAW:2823]ご苦労さまでした。[RAW:2B23-411F-AE1F-4B1F]ただ、もう少し早めに[RAW:2823]教えてほしかったわ…。[RAW:2B23-411F-AE1F-491F]フフッ。[RAW:2823]もう少しで[RAW:2823]寝てしまうところだったもの。[RAW:2B23-411F-AE1F-481F]じゃあ、お礼をあげなきゃね。[RAW:2823]ついてきてちょうだい。[RAW:0E27]",
      "original": "[RAW:411F-AE1F-481F-3621]あらあら。[RAW:2823]お仕事が終わったのね。[RAW:2823]ご苦労さまでした。[RAW:2B23-411F-AE1F-4B1F]ただ、もう少し早めに[RAW:2823]教えてほしかったわ…。[RAW:2B23-411F-AE1F-491F]フフッ。[RAW:2823]もう少しで[RAW:2823]寝てしまうところだったもの。[RAW:2B23-411F-AE1F-481F]じゃあ、お礼をあげなきゃね。[RAW:2823]ついてきてちょうだい。[RAW:0E27]",
      "translation": "[RAW:411F-AE1F-481F-3621]어머나。[RAW:2823]일이 끝났구나。[RAW:2823]수고했어。[RAW:2B23-411F-AE1F-4B1F]다만、좀 더 일찍[RAW:2823]알려 줬으면 했어…。[RAW:2B23-411F-AE1F-491F]후훗。[RAW:2823]조금만 더 있으면[RAW:2823]잠들 뻔했거든。[RAW:2B23-411F-AE1F-481F]그럼、답례를 줘야지。[RAW:2823]따라와 줘。[RAW:0E27]",
      "controls": [
        "[RAW:411F-AE1F-481F-3621]",
        "[RAW:2823]",
        "[RAW:2823]",
        "[RAW:2B23-411F-AE1F-4B1F]",
        "[RAW:2823]",
        "[RAW:2B23-411F-AE1F-491F]",
        "[RAW:2823]",
        "[RAW:2823]",
        "[RAW:2B23-411F-AE1F-481F]",
        "[RAW:2823]",
        "[RAW:0E27]"
      ]
    },
    {
      "index": 13,
      "name": "13",
      "message": "[RAW:411F-AE1F-491F-3621]あらあら。[RAW:2823]お仕事が終わったのね。[RAW:2823]ご苦労さまでした。[RAW:2B23-411F-AE1F-4C1F]そういえば[RAW:2823]とちゅうから[RAW:2823]雨になってしまったわね…。[RAW:2B23]せっかく来てくれたのに[RAW:2823]ごめんなさいね。[RAW:2B23]お礼だけでも[RAW:2823]持ってってちょうだい。[RAW:0E27]",
      "original": "[RAW:411F-AE1F-491F-3621]あらあら。[RAW:2823]お仕事が終わったのね。[RAW:2823]ご苦労さまでした。[RAW:2B23-411F-AE1F-4C1F]そういえば[RAW:2823]とちゅうから[RAW:2823]雨になってしまったわね…。[RAW:2B23]せっかく来てくれたのに[RAW:2823]ごめんなさいね。[RAW:2B23]お礼だけでも[RAW:2823]持ってってちょうだい。[RAW:0E27]",
      "translation": "[RAW:411F-AE1F-491F-3621]어머나。[RAW:2823]일이 끝났구나。[RAW:2823]수고했어。[RAW:2B23-411F-AE1F-4C1F]그러고 보니[RAW:2823]도중에[RAW:2823]비가 와 버렸네…。[RAW:2B23]모처럼 와 줬는데[RAW:2823]미안해。[RAW:2B23]답례만이라도[RAW:2823]가져가 줘。[RAW:0E27]",
      "controls": [
        "[RAW:411F-AE1F-491F-3621]",
        "[RAW:2823]",
        "[RAW:2823]",
        "[RAW:2B23-411F-AE1F-4C1F]",
        "[RAW:2823]",
        "[RAW:2823]",
        "[RAW:2B23]",
        "[RAW:2823]",
        "[RAW:2B23]",
        "[RAW:2823]",
        "[RAW:0E27]"
      ]
    },
    {
      "index": 14,
      "name": "14",
      "message": "[RAW:411F-AE1F-481F-3621]さすがね。[RAW:2823]ていねいな仕事で[RAW:2823]とっても助かるわ。[RAW:2B23-411F-AE1F-491F]フフッ。[RAW:2823]少ないけど、これはお礼よ。[RAW:2823]受け取ってちょうだい。[RAW:0E27]",
      "original": "[RAW:411F-AE1F-481F-3621]さすがね。[RAW:2823]ていねいな仕事で[RAW:2823]とっても助かるわ。[RAW:2B23-411F-AE1F-491F]フフッ。[RAW:2823]少ないけど、これはお礼よ。[RAW:2823]受け取ってちょうだい。[RAW:0E27]",
      "translation": "[RAW:411F-AE1F-481F-3621]역시 대단해。[RAW:2823]꼼꼼한 일솜씨라[RAW:2823]정말 도움이 돼。[RAW:2B23-411F-AE1F-491F]후훗。[RAW:2823]적지만、이건 답례야。[RAW:2823]받아 주겠니。[RAW:0E27]",
      "controls": [
        "[RAW:411F-AE1F-481F-3621]",
        "[RAW:2823]",
        "[RAW:2823]",
        "[RAW:2B23-411F-AE1F-491F]",
        "[RAW:2823]",
        "[RAW:2823]",
        "[RAW:0E27]"
      ]
    },
    {
      "index": 15,
      "name": "15",
      "message": "[RAW:411F-C61F-481F-3621-6D20]★ＥＲＲＯＲ！★[RAW:6C20-0E27]",
      "original": "[RAW:411F-C61F-481F-3621-6D20]★ＥＲＲＯＲ！★[RAW:6C20-0E27]",
      "translation": "[RAW:411F-C61F-481F-3621-6D20]★ＥＲＲＯＲ！★[RAW:6C20-0E27]",
      "controls": [
        "[RAW:411F-C61F-481F-3621-6D20]",
        "[RAW:6C20-0E27]"
      ]
    },
    {
      "index": 16,
      "name": "16",
      "message": "[RAW:411F-C61F-481F-3621-6D20]★ＥＲＲＯＲ！★[RAW:6C20-0E27]",
      "original": "[RAW:411F-C61F-481F-3621-6D20]★ＥＲＲＯＲ！★[RAW:6C20-0E27]",
      "translation": "[RAW:411F-C61F-481F-3621-6D20]★ＥＲＲＯＲ！★[RAW:6C20-0E27]",
      "controls": [
        "[RAW:411F-C61F-481F-3621-6D20]",
        "[RAW:6C20-0E27]"
      ]
    },
    {
      "index": 17,
      "name": "17",
      "message": "[RAW:411F-AE1F-491F-3621]あと、これはオマケ。[RAW:2823]早くおわらせてくれたから[RAW:2823]助かったわ。[RAW:0E27]",
      "original": "[RAW:411F-AE1F-491F-3621]あと、これはオマケ。[RAW:2823]早くおわらせてくれたから[RAW:2823]助かったわ。[RAW:0E27]",
      "translation": "[RAW:411F-AE1F-491F-3621]그리고、이건 덤이야。[RAW:2823]빨리 끝내 줘서[RAW:2823]도움이 됐어。[RAW:0E27]",
      "controls": [
        "[RAW:411F-AE1F-491F-3621]",
        "[RAW:2823]",
        "[RAW:2823]",
        "[RAW:0E27]"
      ]
    },
    {
      "index": 18,
      "name": "18",
      "message": "[RAW:3721-0110]を[RAW:2823]受け取った！[RAW:0E27]",
      "original": "[RAW:3721-0110]を[RAW:2823]受け取った！[RAW:0E27]",
      "translation": "[RAW:3721-0110]를[RAW:2823]받았다！[RAW:0E27]",
      "controls": [
        "[RAW:3721-0110]",
        "[RAW:2823]",
        "[RAW:0E27]"
      ]
    },
    {
      "index": 19,
      "name": "19",
      "message": "[RAW:411F-AE1F-491F-3621]どうもありがとう。[RAW:2823]これからもよろしく[RAW:2823]お願いしますね。[RAW:0E27]",
      "original": "[RAW:411F-AE1F-491F-3621]どうもありがとう。[RAW:2823]これからもよろしく[RAW:2823]お願いしますね。[RAW:0E27]",
      "translation": "[RAW:411F-AE1F-491F-3621]정말 고마워。[RAW:2823]앞으로도 잘[RAW:2823]부탁할게。[RAW:0E27]",
      "controls": [
        "[RAW:411F-AE1F-491F-3621]",
        "[RAW:2823]",
        "[RAW:2823]",
        "[RAW:0E27]"
      ]
    },
    {
      "index": 20,
      "name": "20",
      "message": "[RAW:3721]たのまれた仕事を[RAW:2823]やりとげた！[RAW:0E27-0F27]‘",
      "original": "[RAW:3721]たのまれた仕事を[RAW:2823]やりとげた！[RAW:0E27-0F27]‘",
      "translation": "[RAW:3721]부탁받은 일을[RAW:2823]해냈다！[RAW:0E27-0F27]‘",
      "controls": [
        "[RAW:3721]",
        "[RAW:2823]",
        "[RAW:0E27-0F27]"
      ]
    }
  ]
}